.gitignore
.pre-commit-config.yaml
AUTHORS
BADGES.rst
CHANGES
LICENSE
MANIFEST.in
README.rst
pyproject.toml
setup.cfg
setup.py
.github/pull_request_template.md
.github/workflows/ci.yml
.github/workflows/lint-autoupdate.yml
.github/workflows/lint.yml
flexcache/__init__.py
flexcache/flexcache.py
flexcache.egg-info/PKG-INFO
flexcache.egg-info/SOURCES.txt
flexcache.egg-info/dependency_links.txt
flexcache.egg-info/requires.txt
flexcache.egg-info/top_level.txt
flexcache.egg-info/zip-safe
flexcache/testsuite/__init__.py
flexcache/testsuite/test_byhash.py
flexcache/testsuite/test_bymtime.py
flexcache/testsuite/test_custom_diskcache.py
flexcache/testsuite/test_header.py